htf_overton_instruments/__init__.py
htf_overton_instruments/__version__.py
htf_overton_instruments/device.py
htf_overton_instruments/interface.py
tests/__init__.py
tests/receiver.py
htf_overton_instruments-2021.2.dist-info/LICENSE.txt
htf_overton_instruments-2021.2.dist-info/METADATA
htf_overton_instruments-2021.2.dist-info/WHEEL
htf_overton_instruments-2021.2.dist-info/top_level.txt
htf_overton_instruments-2021.2.dist-info/RECORD
