Metadata-Version: 2.1
Name: htf-overton-instruments
Version: 2021.2
Summary: Add-on package for the Hilster Testing Framework which enablestesting Overton Instrument devices.
Home-page: https://github.com/overton-instruments/htf-overton-instruments
Author: Overton Instruments
Author-email: overton@overtoninstruments.com
License: MIT
Keywords: htf,overton,HILSTER,Testing
Platform: UNKNOWN
Classifier: Development Status :: 5 - Production/Stable
Classifier: Intended Audience :: Developers
Classifier: Topic :: Software Development :: Build Tools
Classifier: License :: OSI Approved :: MIT License
Classifier: Programming Language :: Python :: 3
Requires-Dist: htf (>=2.0)
